srv_test/__init__.py
srv_test/srv_test.py
srv_test/test.py
srv_test/srv_test/__init__.py
srv_test/srv_test/__main__.py
srv_test/srv_test/srv_test_main.py
srv_test-0.4.25.data/data/etc/srv_test/srv_test.install.sh
srv_test-0.4.25.data/data/etc/srv_test/srv_test.yml
srv_test-0.4.25.data/data/etc/systemd/system/srv_test.service
srv_test-0.4.25.data/data/etc/systemd/system/srv_test.socket
srv_test-0.4.25.data/data/usr/local/lib/srv_test/srv_test.py
srv_test-0.4.25.data/scripts/srv_test.install.sh
srv_test-0.4.25.dist-info/LICENSE
srv_test-0.4.25.dist-info/METADATA
srv_test-0.4.25.dist-info/WHEEL
srv_test-0.4.25.dist-info/entry_points.txt
srv_test-0.4.25.dist-info/top_level.txt
srv_test-0.4.25.dist-info/RECORD
