Metadata-Version: 2.1
Name: srv-test
Version: 0.4.25
Summary: SRV TEST
Home-page: http://github/bartoszkaron/srv_test/
Author: Bartosz Karon
Author-email: bartosz.karon@gmail.com
License: MIT
Platform: UNKNOWN
Classifier: Programming Language :: Python :: 3.10
License-File: LICENSE
Requires-Dist: pysocket
Requires-Dist: pyyaml
